tsai/__init__.py
tsai/_modidx.py
tsai/_nbdev.py
tsai/all.py
tsai/analysis.py
tsai/basics.py
tsai/calibration.py
tsai/export.py
tsai/imports.py
tsai/index.py
tsai/inference.py
tsai/learner.py
tsai/losses.py
tsai/metrics.py
tsai/optimizer.py
tsai/optuna.py
tsai/tslearner.py
tsai/tutorials.py
tsai/utils.py
tsai/wandb.py
tsai/callback/MVP.py
tsai/callback/PredictionDynamics.py
tsai/callback/__init__.py
tsai/callback/all.py
tsai/callback/core.py
tsai/callback/experimental.py
tsai/callback/noisy_student.py
tsai/data/__init__.py
tsai/data/all.py
tsai/data/basics.py
tsai/data/core.py
tsai/data/external.py
tsai/data/features.py
tsai/data/image.py
tsai/data/metadatasets.py
tsai/data/mixed.py
tsai/data/mixed_augmentation.py
tsai/data/preparation.py
tsai/data/preprocessing.py
tsai/data/tabular.py
tsai/data/transforms.py
tsai/data/unwindowed.py
tsai/data/validation.py
tsai/models/ConvTranPlus.py
tsai/models/FCN.py
tsai/models/FCNPlus.py
tsai/models/GatedTabTransformer.py
tsai/models/HydraMultiRocketPlus.py
tsai/models/HydraPlus.py
tsai/models/InceptionTime.py
tsai/models/InceptionTimePlus.py
tsai/models/MINIROCKET.py
tsai/models/MINIROCKETPlus_Pytorch.py
tsai/models/MINIROCKET_Pytorch.py
tsai/models/MLP.py
tsai/models/MultiInputNet.py
tsai/models/MultiRocketPlus.py
tsai/models/OmniScaleCNN.py
tsai/models/PatchTST.py
tsai/models/RNN.py
tsai/models/RNNAttention.py
tsai/models/RNNAttentionPlus.py
tsai/models/RNNPlus.py
tsai/models/RNN_FCN.py
tsai/models/RNN_FCNPlus.py
tsai/models/ROCKET.py
tsai/models/ROCKET_Pytorch.py
tsai/models/ResCNN.py
tsai/models/ResNet.py
tsai/models/ResNetPlus.py
tsai/models/TCN.py
tsai/models/TSPerceiver.py
tsai/models/TSSequencerPlus.py
tsai/models/TST.py
tsai/models/TSTPlus.py
tsai/models/TSiTPlus.py
tsai/models/TabFusionTransformer.py
tsai/models/TabModel.py
tsai/models/TabTransformer.py
tsai/models/TransformerModel.py
tsai/models/TransformerRNNPlus.py
tsai/models/XCM.py
tsai/models/XCMPlus.py
tsai/models/XResNet1d.py
tsai/models/XResNet1dPlus.py
tsai-0.4.1.dist-info/licenses/LICENSE
tsai-0.4.1.dist-info/METADATA
tsai-0.4.1.dist-info/WHEEL
tsai-0.4.1.dist-info/entry_points.txt
tsai-0.4.1.dist-info/top_level.txt
tsai-0.4.1.dist-info/RECORD
