Metadata-Version: 2.4
Name: tsai
Version: 0.4.1
Summary: Practical Deep Learning for Time Series / Sequential Data library based on fastai & Pytorch
Home-page: https://github.com/timeseriesAI/tsai/
Author: Ignacio Oguiza and contributors
Author-email: oguiza@timeseriesAI.co
License: Apache Software License 2.0
Keywords: fastai time-series time-series-classification time-series-regression deep-learning Pytorch
Classifier: Development Status :: 5 - Production/Stable
Classifier: Intended Audience :: Developers
Classifier: License :: OSI Approved :: Apache Software License
Classifier: Natural Language :: English
Classifier: Programming Language :: Python :: 3.9
Classifier: Programming Language :: Python :: 3.10
Classifier: Programming Language :: Python :: 3.11
Classifier: Programming Language :: Python :: 3.12
Classifier: Programming Language :: Python :: 3.13
Requires-Python: >=3.9
License-File: LICENSE
Requires-Dist: pip
Requires-Dist: packaging
Requires-Dist: fastai>=2.8.2
Requires-Dist: pyts>=0.13.0
Requires-Dist: imbalanced-learn>=0.12.4
Requires-Dist: psutil>=6.1.0
Requires-Dist: scikit-learn>=1.5.2
Requires-Dist: torch<2.8,>=1.10
Provides-Extra: dev
Requires-Dist: nbdev>2; extra == "dev"
Requires-Dist: ipykernel>6; extra == "dev"
Requires-Dist: ipython<9; extra == "dev"
Provides-Extra: extras
Requires-Dist: sktime>=0.38.4; extra == "extras"
Requires-Dist: tsfresh>=0.21.0; extra == "extras"
Requires-Dist: PyWavelets>=1.8.0; extra == "extras"
Requires-Dist: nbformat>=5.10.4; extra == "extras"
Dynamic: author
Dynamic: author-email
Dynamic: classifier
Dynamic: description
Dynamic: description-content-type
Dynamic: home-page
Dynamic: keywords
Dynamic: license
Dynamic: license-file
Dynamic: provides-extra
Dynamic: requires-dist
Dynamic: requires-python
Dynamic: summary
